smart_admin/__init__.py
smart_admin/apps.py
smart_admin/autocomplete.py
smart_admin/changelist.py
smart_admin/checks.py
smart_admin/decorators.py
smart_admin/mixins.py
smart_admin/modeladmin.py
smart_admin/settings.py
smart_admin/site.py
smart_admin/truncate.py
smart_admin/utils.py
smart_admin/version.py
smart_admin/console/__init__.py
smart_admin/console/email.py
smart_admin/console/error_pages.py
smart_admin/console/migrations.py
smart_admin/console/redis.py
smart_admin/console/sentry.py
smart_admin/console/sysinfo.py
smart_admin/logs/__init__.py
smart_admin/logs/admin.py
smart_admin/logs/apps.py
smart_admin/logs/models.py
smart_admin/logs/migrations/0001_initial.py
smart_admin/logs/migrations/0002_auto_20210829_1146.py
smart_admin/logs/migrations/__init__.py
smart_admin/smart_auth/__init__.py
smart_admin/smart_auth/admin.py
smart_admin/static/smart_admin/console.css
smart_admin/static/smart_admin/console.css.map
smart_admin/static/smart_admin/console.scss
smart_admin/static/smart_admin/smart_admin.css
smart_admin/static/smart_admin/smart_admin.css.map
smart_admin/static/smart_admin/smart_admin.scss
smart_admin/templates/admin/base_site.html
smart_admin/templates/admin/group_index.html
smart_admin/templates/admin/index.html
smart_admin/templates/admin/nav_sidebar.html
smart_admin/templates/admin/search_form.html
smart_admin/templates/admin/smart_index.html
smart_admin/templates/admin/smart_list.html
smart_admin/templates/admin/auth/group/members.html
smart_admin/templates/admin/auth/group/object_history.html
smart_admin/templates/admin/auth/permission/users.html
smart_admin/templates/admin/auth/user/object_history.html
smart_admin/templates/admin/auth/user/permissions.html
smart_admin/templates/admin/logentry/archive.html
smart_admin/templates/admin/logentry/change_form.html
smart_admin/templates/admin/logentry/truncate.html
smart_admin/templates/admin/sysinfo/sysinfo_section.html
smart_admin/templates/smart_admin/console.html
django_smart_admin-3.0.dist-info/METADATA
django_smart_admin-3.0.dist-info/WHEEL
django_smart_admin-3.0.dist-info/RECORD
