Metadata-Version: 2.4
Name: django-smart-admin
Version: 3.0
Summary: Collection of small Django Admin utilities that aims to remove some of the common annoying configuration issues
Classifier: Programming Language :: Python :: 3 :: Only
Classifier: Programming Language :: Python :: 3.10
Classifier: Programming Language :: Python :: 3.11
Classifier: Programming Language :: Python :: 3.12
Classifier: Programming Language :: Python :: 3.13
Requires-Python: >=3.10
Requires-Dist: django-admin-extra-buttons>=2.1
Requires-Dist: django-adminfilters>=2.6
Provides-Extra: sysinfo
Requires-Dist: django-sysinfo>=2.7; extra == 'sysinfo'
